aclogin/__init__.py
aclogin/cli.py
aclogin-0.2.1.dist-info/licenses/LICENSE
aclogin-0.2.1.dist-info/METADATA
aclogin-0.2.1.dist-info/WHEEL
aclogin-0.2.1.dist-info/entry_points.txt
aclogin-0.2.1.dist-info/top_level.txt
aclogin-0.2.1.dist-info/RECORD
